{
"type": "FeatureCollection",
"name": "Barhabise_Evacuation_center",
"crs": { "type": "name", "properties": { "name": "urn:ogc:def:crs:OGC:1.3:CRS84" } },
"features": [
{ "type": "Feature", "properties": { "lhNnf": null, "F_ofgLo_tx": null, "j8f_g__": "%", "6f_n": "tNnf] l;+ufr]{", "k_sf_": null, "gfd": "afx|la;] cfkt\\sfnLg cf>o :yn", "Latitude": 0.0, "Longitude": 0.0, "Ward": 5, "Type": "Evacuation Shelter", "Name": "Barhabise Evacuation Shelter", "Capacity": 50, "Room": 2, "PWD_inclus": "Yes" }, "geometry": { "type": "Point", "coordinates": [ 85.887453949137097, 27.815145432761931 ] } }
]
}
